crayon.py
crayon-0.4.dist-info/DESCRIPTION.rst
crayon-0.4.dist-info/METADATA
crayon-0.4.dist-info/RECORD
crayon-0.4.dist-info/WHEEL
crayon-0.4.dist-info/metadata.json
crayon-0.4.dist-info/top_level.txt
