Metadata-Version: 2.0
Name: crayon
Version: 0.4
Summary: Utility for styling terminal text output
Home-page: https://github.com/lukaskubis/crayon
Author: Lukas Kubis
Author-email: contact@lukaskubis.com
License: MIT
Keywords: color style terminal text utility
Platform: UNKNOWN
Classifier: Development Status :: 4 - Beta
Classifier: Topic :: Software Development :: Libraries :: Python Modules
Classifier: License :: OSI Approved :: MIT License
Classifier: Programming Language :: Python :: 2
Classifier: Programming Language :: Python :: 3
